icplazapy/__init__.py
icplazapy/_transaction.py
icplazapy/_wallet.py
icplazapy/py.typed
icplazapy/typing.py
icplazapy-3.0.0.dist-info/LICENSE
icplazapy-3.0.0.dist-info/WHEEL
icplazapy-3.0.0.dist-info/METADATA
icplazapy-3.0.0.dist-info/RECORD
