Metadata-Version: 2.1
Name: icplazapy
Version: 3.0.0
Summary: Tools for Icplaza wallet management and offline transaction signing
Keywords: icplaza,evmos,cosmos,blockchain,atom,cryptocurrency
Author-email: chuanfoo <442837306@qq.com>
Requires-Python: >=3.7
Classifier: Intended Audience :: Developers
Classifier: License :: OSI Approved :: MIT License
Classifier: Natural Language :: English
Classifier: Topic :: Software Development :: Libraries :: Python Modules
Classifier: Typing :: Typed
Requires-Dist: ecdsa >=0.14.0
Requires-Dist: bech32 >=1.1.0
Requires-Dist: mnemonic >=0.19
Requires-Dist: hdwallets >=0.1.0
Requires-Dist: typing-extensions >=3.7.4; python_version < '3.8'
Project-URL: Changelog, https://github.com/ICPLAZA-org/icplazapy/blob/master/CHANGELOG.md
Project-URL: Homepage, https://github.com/ICPLAZA-org/icplazapy
